moseley/__init__.py
moseley/_modidx.py
moseley/_nbdev.py
moseley/moseley_law.py
moseley/mplot.py
moseley/peak_pattern_atlas.py
moseley/xrf_physics.py
moseley-1.0.3.dist-info/licenses/LICENSE
moseley-1.0.3.dist-info/METADATA
moseley-1.0.3.dist-info/WHEEL
moseley-1.0.3.dist-info/entry_points.txt
moseley-1.0.3.dist-info/top_level.txt
moseley-1.0.3.dist-info/RECORD
